MANIFEST.in
setup.py
bin/hogwatch
hogwatch/.gitignore
hogwatch/__init__.py
hogwatch/__init__.pyc
hogwatch.egg-info/PKG-INFO
hogwatch.egg-info/SOURCES.txt
hogwatch.egg-info/dependency_links.txt
hogwatch.egg-info/requires.txt
hogwatch.egg-info/top_level.txt
hogwatch/server/__init__.py
hogwatch/server/__init__.pyc
hogwatch/server/web_service.py
hogwatch/server/web_service.pyc
hogwatch/server/frontend/README.md
hogwatch/server/frontend/vendor/index.html
hogwatch/server/frontend/vendor/static/css/app.7751c37bb82a77f04be5970ac9c73dbf.css
hogwatch/server/frontend/vendor/static/css/css_reset.css
hogwatch/server/frontend/vendor/static/css/nano.css
hogwatch/server/frontend/vendor/static/fonts/oxygen/oxygen-v5-latin-300.eot
hogwatch/server/frontend/vendor/static/fonts/oxygen/oxygen-v5-latin-300.svg
hogwatch/server/frontend/vendor/static/fonts/oxygen/oxygen-v5-latin-300.ttf
hogwatch/server/frontend/vendor/static/fonts/oxygen/oxygen-v5-latin-300.woff
hogwatch/server/frontend/vendor/static/fonts/oxygen/oxygen-v5-latin-300.woff2
hogwatch/server/frontend/vendor/static/fonts/oxygen/oxygen-v5-latin-700.eot
hogwatch/server/frontend/vendor/static/fonts/oxygen/oxygen-v5-latin-700.svg
hogwatch/server/frontend/vendor/static/fonts/oxygen/oxygen-v5-latin-700.ttf
hogwatch/server/frontend/vendor/static/fonts/oxygen/oxygen-v5-latin-700.woff
hogwatch/server/frontend/vendor/static/fonts/oxygen/oxygen-v5-latin-700.woff2
hogwatch/server/frontend/vendor/static/fonts/oxygen/oxygen-v5-latin-regular.eot
hogwatch/server/frontend/vendor/static/fonts/oxygen/oxygen-v5-latin-regular.svg
hogwatch/server/frontend/vendor/static/fonts/oxygen/oxygen-v5-latin-regular.ttf
hogwatch/server/frontend/vendor/static/fonts/oxygen/oxygen-v5-latin-regular.woff
hogwatch/server/frontend/vendor/static/fonts/oxygen/oxygen-v5-latin-regular.woff2
hogwatch/server/frontend/vendor/static/images/clock.svg
hogwatch/server/frontend/vendor/static/images/github.svg
hogwatch/server/frontend/vendor/static/images/mail.svg
hogwatch/server/frontend/vendor/static/images/python.svg
hogwatch/server/frontend/vendor/static/js/app.f240c2e65800ee4c3ec7.js
