Metadata-Version: 1.0
Name: hogwatch
Version: 0.1.9
Summary: find out whats hogging your internet
Home-page: https://github.com/akshayKMR/hogwatch
Author: Akshay Kumar
Author-email: akshay.kmr4321@gmail.com
License: MIT
Platform: UNKNOWN
